{"type": "GameHistory", "white_name": "TroutBot", "black_name": "GnashBot", "senses": {"true": [16, 63, 27, 51, 60, 41, 38, 36, 35, 11, 14, 24, 12, 48, 24, 36, 12, 27, 24, 27, 6, 51, 46, 9, 12, 40, 27, 45, 7, 5, 53], "false": [20, 19, 9, 19, 10, 13, 29, 43, 11, 25, 25, 12, 14, 13, 9, 12, 29, 11, 11, 9, 50, 14, 13, 9, 13, 17, 13, 14, 14, 25, 22]}, "sense_results": {"true": [[[24, null], [25, null], [16, null], [17, null], [8, {"type": "Piece", "value": "P"}], [9, {"type": "Piece", "value": "P"}]], [[62, {"type": "Piece", "value": "n"}], [63, {"type": "Piece", "value": "r"}], [54, {"type": "Piece", "value": "p"}], [55, {"type": "Piece", "value": "p"}]], [[34, null], [35, null], [36, null], [26, null], [27, {"type": "Piece", "value": "p"}], [28, {"type": "Piece", "value": "P"}], [18, null], [19, null], [20, null]], [[58, {"type": "Piece", "value": "b"}], [59, {"type": "Piece", "value": "q"}], [60, {"type": "Piece", "value": "k"}], [50, null], [51, {"type": "Piece", "value": "p"}], [52, {"type": "Piece", "value": "p"}], [42, {"type": "Piece", "value": "n"}], [43, null], [44, null]], [[59, {"type": "Piece", "value": "q"}], [60, {"type": "Piece", "value": "k"}], [61, {"type": "Piece", "value": "b"}], [51, {"type": "Piece", "value": "p"}], [52, {"type": "Piece", "value": "p"}], [53, {"type": "Piece", "value": "p"}]], [[48, {"type": "Piece", "value": "p"}], [49, {"type": "Piece", "value": "p"}], [50, null], [40, null], [41, null], [42, {"type": "Piece", "value": "n"}], [32, null], [33, null], [34, null]], [[45, {"type": "Piece", "value": "n"}], [46, null], [47, null], [37, null], [38, null], [39, null], [29, null], [30, null], [31, null]], [[43, null], [44, {"type": "Piece", "value": "p"}], [45, {"type": "Piece", "value": "n"}], [35, null], [36, {"type": "Piece", "value": "p"}], [37, null], [27, null], [28, null], [29, null]], [[42, {"type": "Piece", "value": "n"}], [43, null], [44, {"type": "Piece", "value": "p"}], [34, null], [35, null], [36, {"type": "Piece", "value": "p"}], [26, null], [27, null], [28, null]], [[18, {"type": "Piece", "value": "N"}], [19, null], [20, null], [10, {"type": "Piece", "value": "P"}], [11, null], [12, null], [2, {"type": "Piece", "value": "B"}], [3, null], [4, {"type": "Piece", "value": "K"}]], [[21, {"type": "Piece", "value": "N"}], [22, {"type": "Piece", "value": "P"}], [23, null], [13, {"type": "Piece", "value": "P"}], [14, null], [15, {"type": "Piece", "value": "P"}], [5, null], [6, null], [7, {"type": "Piece", "value": "R"}]], [[32, null], [33, null], [24, {"type": "Piece", "value": "b"}], [25, null], [16, null], [17, {"type": "Piece", "value": "P"}]], [[19, null], [20, null], [21, {"type": "Piece", "value": "N"}], [11, null], [12, {"type": "Piece", "value": "n"}], [13, {"type": "Piece", "value": "P"}], [3, null], [4, null], [5, {"type": "Piece", "value": "R"}]], [[56, {"type": "Piece", "value": "r"}], [57, null], [48, {"type": "Piece", "value": "p"}], [49, {"type": "Piece", "value": "p"}], [40, null], [41, null]], [[32, null], [33, null], [24, {"type": "Piece", "value": "n"}], [25, null], [16, null], [17, {"type": "Piece", "value": "P"}]], [[43, null], [44, {"type": "Piece", "value": "p"}], [45, {"type": "Piece", "value": "n"}], [35, null], [36, null], [37, null], [27, null], [28, {"type": "Piece", "value": "p"}], [29, null]], [[19, null], [20, null], [21, null], [11, null], [12, null], [13, {"type": "Piece", "value": "P"}], [3, null], [4, null], [5, {"type": "Piece", "value": "R"}]], [[34, null], [35, null], [36, null], [26, null], [27, {"type": "Piece", "value": "q"}], [28, {"type": "Piece", "value": "p"}], [18, null], [19, null], [20, null]], [[32, null], [33, null], [24, {"type": "Piece", "value": "q"}], [25, null], [16, null], [17, null]], [[34, null], [35, null], [36, null], [26, null], [27, {"type": "Piece", "value": "q"}], [28, {"type": "Piece", "value": "p"}], [18, null], [19, null], [20, null]], [[13, {"type": "Piece", "value": "P"}], [14, {"type": "Piece", "value": "K"}], [15, null], [5, {"type": "Piece", "value": "R"}], [6, null], [7, null]], [[58, null], [59, null], [60, {"type": "Piece", "value": "k"}], [50, null], [51, null], [52, null], [42, null], [43, null], [44, {"type": "Piece", "value": "p"}]], [[53, {"type": "Piece", "value": "p"}], [54, {"type": "Piece", "value": "p"}], [55, {"type": "Piece", "value": "p"}], [45, {"type": "Piece", "value": "n"}], [46, null], [47, null], [37, null], [38, null], [39, null]], [[16, null], [17, null], [18, null], [8, {"type": "Piece", "value": "P"}], [9, null], [10, {"type": "Piece", "value": "P"}], [0, null], [1, null], [2, null]], [[19, null], [20, null], [21, null], [11, null], [12, {"type": "Piece", "value": "q"}], [13, {"type": "Piece", "value": "P"}], [3, null], [4, null], [5, {"type": "Piece", "value": "R"}]], [[48, {"type": "Piece", "value": "p"}], [49, {"type": "Piece", "value": "p"}], [40, null], [41, null], [32, null], [33, null]], [[34, null], [35, null], [36, null], [26, null], [27, null], [28, {"type": "Piece", "value": "n"}], [18, {"type": "Piece", "value": "P"}], [19, null], [20, null]], [[52, null], [53, {"type": "Piece", "value": "p"}], [54, {"type": "Piece", "value": "p"}], [44, {"type": "Piece", "value": "p"}], [45, null], [46, null], [36, null], [37, null], [38, null]], [[14, {"type": "Piece", "value": "K"}], [15, null], [6, null], [7, null]], [[12, null], [13, {"type": "Piece", "value": "P"}], [14, {"type": "Piece", "value": "K"}], [4, {"type": "Piece", "value": "r"}], [5, {"type": "Piece", "value": "q"}], [6, null]], [[60, null], [61, null], [62, null], [52, null], [53, {"type": "Piece", "value": "p"}], [54, {"type": "Piece", "value": "p"}], [44, {"type": "Piece", "value": "p"}], [45, null], [46, {"type": "Piece", "value": "P"}]]], "false": [[[27, null], [28, {"type": "Piece", "value": "P"}], [29, null], [19, null], [20, null], [21, null], [11, {"type": "Piece", "value": "P"}], [12, null], [13, {"type": "Piece", "value": "P"}]], [[26, null], [27, {"type": "Piece", "value": "P"}], [28, {"type": "Piece", "value": "P"}], [18, null], [19, null], [20, null], [10, {"type": "Piece", "value": "P"}], [11, null], [12, null]], [[16, null], [17, null], [18, null], [8, {"type": "Piece", "value": "P"}], [9, {"type": "Piece", "value": "P"}], [10, {"type": "Piece", "value": "P"}], [0, {"type": "Piece", "value": "R"}], [1, {"type": "Piece", "value": "N"}], [2, {"type": "Piece", "value": "B"}]], [[26, null], [27, null], [28, {"type": "Piece", "value": "P"}], [18, null], [19, null], [20, null], [10, {"type": "Piece", "value": "P"}], [11, null], [12, null]], [[17, null], [18, {"type": "Piece", "value": "N"}], [19, null], [9, {"type": "Piece", "value": "P"}], [10, {"type": "Piece", "value": "P"}], [11, null], [1, null], [2, {"type": "Piece", "value": "B"}], [3, null]], [[20, null], [21, {"type": "Piece", "value": "N"}], [22, null], [12, null], [13, {"type": "Piece", "value": "P"}], [14, {"type": "Piece", "value": "P"}], [4, {"type": "Piece", "value": "K"}], [5, {"type": "Piece", "value": "B"}], [6, null]], [[36, {"type": "Piece", "value": "P"}], [37, null], [38, null], [28, null], [29, null], [30, null], [20, null], [21, {"type": "Piece", "value": "N"}], [22, null]], [[50, null], [51, null], [52, null], [42, {"type": "Piece", "value": "n"}], [43, null], [44, {"type": "Piece", "value": "p"}], [34, null], [35, null], [36, {"type": "Piece", "value": "p"}]], [[18, {"type": "Piece", "value": "N"}], [19, null], [20, null], [10, {"type": "Piece", "value": "P"}], [11, null], [12, null], [2, {"type": "Piece", "value": "B"}], [3, null], [4, {"type": "Piece", "value": "K"}]], [[32, null], [33, null], [34, {"type": "Piece", "value": "b"}], [24, {"type": "Piece", "value": "Q"}], [25, null], [26, null], [16, null], [17, {"type": "Piece", "value": "P"}], [18, {"type": "Piece", "value": "N"}]], [[32, null], [33, null], [34, {"type": "Piece", "value": "b"}], [24, {"type": "Piece", "value": "Q"}], [25, null], [26, null], [16, null], [17, {"type": "Piece", "value": "P"}], [18, {"type": "Piece", "value": "N"}]], [[19, null], [20, null], [21, {"type": "Piece", "value": "N"}], [11, null], [12, {"type": "Piece", "value": "B"}], [13, {"type": "Piece", "value": "P"}], [3, null], [4, null], [5, {"type": "Piece", "value": "R"}]], [[21, {"type": "Piece", "value": "N"}], [22, {"type": "Piece", "value": "P"}], [23, null], [13, {"type": "Piece", "value": "P"}], [14, {"type": "Piece", "value": "K"}], [15, {"type": "Piece", "value": "P"}], [5, {"type": "Piece", "value": "R"}], [6, null], [7, null]], [[20, null], [21, {"type": "Piece", "value": "N"}], [22, {"type": "Piece", "value": "P"}], [12, null], [13, {"type": "Piece", "value": "P"}], [14, {"type": "Piece", "value": "K"}], [4, null], [5, {"type": "Piece", "value": "R"}], [6, null]], [[16, null], [17, null], [18, null], [8, {"type": "Piece", "value": "P"}], [9, {"type": "Piece", "value": "B"}], [10, {"type": "Piece", "value": "P"}], [0, {"type": "Piece", "value": "R"}], [1, null], [2, null]], [[19, null], [20, null], [21, null], [11, null], [12, null], [13, {"type": "Piece", "value": "P"}], [3, null], [4, null], [5, {"type": "Piece", "value": "R"}]], [[36, null], [37, null], [38, null], [28, {"type": "Piece", "value": "p"}], [29, null], [30, null], [20, null], [21, null], [22, {"type": "Piece", "value": "P"}]], [[18, null], [19, null], [20, null], [10, {"type": "Piece", "value": "P"}], [11, null], [12, {"type": "Piece", "value": "N"}], [2, null], [3, null], [4, null]], [[18, null], [19, null], [20, null], [10, {"type": "Piece", "value": "P"}], [11, null], [12, null], [2, null], [3, null], [4, null]], [[16, null], [17, null], [18, null], [8, {"type": "Piece", "value": "P"}], [9, null], [10, {"type": "Piece", "value": "P"}], [0, {"type": "Piece", "value": "R"}], [1, null], [2, null]], [[57, null], [58, null], [59, null], [49, {"type": "Piece", "value": "p"}], [50, null], [51, null], [41, null], [42, null], [43, null]], [[21, {"type": "Piece", "value": "q"}], [22, {"type": "Piece", "value": "P"}], [23, {"type": "Piece", "value": "P"}], [13, {"type": "Piece", "value": "P"}], [14, null], [15, null], [5, {"type": "Piece", "value": "R"}], [6, {"type": "Piece", "value": "K"}], [7, null]], [[20, {"type": "Piece", "value": "p"}], [21, {"type": "Piece", "value": "q"}], [22, null], [12, null], [13, {"type": "Piece", "value": "P"}], [14, null], [4, {"type": "Piece", "value": "R"}], [5, {"type": "Piece", "value": "R"}], [6, {"type": "Piece", "value": "K"}]], [[16, null], [17, null], [18, null], [8, {"type": "Piece", "value": "P"}], [9, null], [10, {"type": "Piece", "value": "P"}], [0, null], [1, null], [2, null]], [[20, null], [21, null], [22, null], [12, {"type": "Piece", "value": "q"}], [13, {"type": "Piece", "value": "P"}], [14, null], [4, null], [5, {"type": "Piece", "value": "R"}], [6, {"type": "Piece", "value": "K"}]], [[24, null], [25, null], [26, null], [16, {"type": "Piece", "value": "P"}], [17, null], [18, {"type": "Piece", "value": "P"}], [8, null], [9, null], [10, null]], [[20, null], [21, null], [22, null], [12, {"type": "Piece", "value": "q"}], [13, {"type": "Piece", "value": "P"}], [14, {"type": "Piece", "value": "K"}], [4, null], [5, {"type": "Piece", "value": "R"}], [6, null]], [[21, null], [22, null], [23, {"type": "Piece", "value": "P"}], [13, {"type": "Piece", "value": "P"}], [14, {"type": "Piece", "value": "K"}], [15, null], [5, {"type": "Piece", "value": "R"}], [6, null], [7, null]], [[21, null], [22, null], [23, {"type": "Piece", "value": "P"}], [13, {"type": "Piece", "value": "P"}], [14, {"type": "Piece", "value": "K"}], [15, null], [5, {"type": "Piece", "value": "R"}], [6, null], [7, null]], [[32, null], [33, null], [34, null], [24, null], [25, null], [26, null], [16, {"type": "Piece", "value": "P"}], [17, null], [18, {"type": "Piece", "value": "P"}]], [[29, null], [30, null], [31, null], [21, {"type": "Piece", "value": "K"}], [22, null], [23, {"type": "Piece", "value": "P"}], [13, {"type": "Piece", "value": "P"}], [14, null], [15, null]]]}, "requested_moves": {"true": [{"type": "Move", "value": "e2e4"}, {"type": "Move", "value": "d2d4"}, {"type": "Move", "value": "d1d4"}, {"type": "Move", "value": "d4a4"}, {"type": "Move", "value": "b1c3"}, {"type": "Move", "value": "g1f3"}, {"type": "Move", "value": "e4e5"}, {"type": "Move", "value": "b2b3"}, {"type": "Move", "value": "g2g3"}, {"type": "Move", "value": "f1e2"}, {"type": "Move", "value": "e1g1"}, {"type": "Move", "value": "c3a4"}, {"type": "Move", "value": "g1g2"}, {"type": "Move", "value": "c1b2"}, {"type": "Move", "value": "b3a4"}, {"type": "Move", "value": "f3g1"}, {"type": "Move", "value": "b2f6"}, {"type": "Move", "value": "g1e2"}, {"type": "Move", "value": "e2d4"}, {"type": "Move", "value": "h2h3"}, {"type": "Move", "value": "g2g1"}, {"type": "Move", "value": "a1e1"}, {"type": "Move", "value": "g3g4"}, {"type": "Move", "value": "e1e2"}, {"type": "Move", "value": "a2a3"}, {"type": "Move", "value": "c2c3"}, {"type": "Move", "value": "g1g2"}, {"type": "Move", "value": "g4g5"}, {"type": "Move", "value": "g5g6"}, {"type": "Move", "value": "g2f3"}, null], "false": [{"type": "Move", "value": "c7c5"}, {"type": "Move", "value": "c5d4"}, {"type": "Move", "value": "b8c6"}, {"type": "Move", "value": "g8f6"}, {"type": "Move", "value": "e7e6"}, {"type": "Move", "value": "d7d6"}, {"type": "Move", "value": "d6e5"}, {"type": "Move", "value": "c8d7"}, {"type": "Move", "value": "f8c5"}, {"type": "Move", "value": "c6d4"}, {"type": "Move", "value": "d7a4"}, {"type": "Move", "value": "d4e2"}, {"type": "Move", "value": "e2c3"}, {"type": "Move", "value": "c3a4"}, {"type": "Move", "value": "e5e4"}, {"type": "Move", "value": "c5d4"}, {"type": "Move", "value": "d8d4"}, {"type": "Move", "value": "d4a4"}, {"type": "Move", "value": "a4d4"}, {"type": "Move", "value": "d4c3"}, {"type": "Move", "value": "c3f3"}, {"type": "Move", "value": "e4e3"}, {"type": "Move", "value": "e3e2"}, {"type": "Move", "value": "f3e2"}, {"type": "Move", "value": "e8c8"}, {"type": "Move", "value": "f6e4"}, {"type": "Move", "value": "d8d1"}, {"type": "Move", "value": "d1e1"}, {"type": "Move", "value": "e2f1"}, {"type": "Move", "value": "f1h1"}, {"type": "Move", "value": "h1f3"}]}, "taken_moves": {"true": [{"type": "Move", "value": "e2e4"}, {"type": "Move", "value": "d2d4"}, {"type": "Move", "value": "d1d4"}, {"type": "Move", "value": "d4a4"}, {"type": "Move", "value": "b1c3"}, {"type": "Move", "value": "g1f3"}, {"type": "Move", "value": "e4e5"}, {"type": "Move", "value": "b2b3"}, {"type": "Move", "value": "g2g3"}, {"type": "Move", "value": "f1e2"}, {"type": "Move", "value": "e1g1"}, {"type": "Move", "value": "c3a4"}, {"type": "Move", "value": "g1g2"}, {"type": "Move", "value": "c1b2"}, {"type": "Move", "value": "b3a4"}, {"type": "Move", "value": "f3g1"}, {"type": "Move", "value": "b2d4"}, {"type": "Move", "value": "g1e2"}, {"type": "Move", "value": "e2d4"}, {"type": "Move", "value": "h2h3"}, {"type": "Move", "value": "g2g1"}, {"type": "Move", "value": "a1e1"}, {"type": "Move", "value": "g3g4"}, {"type": "Move", "value": "e1e2"}, {"type": "Move", "value": "a2a3"}, {"type": "Move", "value": "c2c3"}, {"type": "Move", "value": "g1g2"}, {"type": "Move", "value": "g4g5"}, {"type": "Move", "value": "g5g6"}, {"type": "Move", "value": "g2f3"}, null], "false": [{"type": "Move", "value": "c7c5"}, {"type": "Move", "value": "c5d4"}, {"type": "Move", "value": "b8c6"}, {"type": "Move", "value": "g8f6"}, {"type": "Move", "value": "e7e6"}, {"type": "Move", "value": "d7d6"}, {"type": "Move", "value": "d6e5"}, {"type": "Move", "value": "c8d7"}, {"type": "Move", "value": "f8c5"}, {"type": "Move", "value": "c6d4"}, {"type": "Move", "value": "d7a4"}, {"type": "Move", "value": "d4e2"}, {"type": "Move", "value": "e2c3"}, {"type": "Move", "value": "c3a4"}, {"type": "Move", "value": "e5e4"}, {"type": "Move", "value": "c5d4"}, {"type": "Move", "value": "d8d4"}, {"type": "Move", "value": "d4a4"}, {"type": "Move", "value": "a4d4"}, {"type": "Move", "value": "d4c3"}, {"type": "Move", "value": "c3f3"}, {"type": "Move", "value": "e4e3"}, {"type": "Move", "value": "e3e2"}, {"type": "Move", "value": "f3e2"}, {"type": "Move", "value": "e8c8"}, {"type": "Move", "value": "f6e4"}, {"type": "Move", "value": "d8d1"}, {"type": "Move", "value": "d1e1"}, {"type": "Move", "value": "e2f1"}, {"type": "Move", "value": "f1h1"}, {"type": "Move", "value": "h1f3"}]}, "capture_squares": {"true": [null, null, 27, null, null, null, null, null, null, null, null, 24, null, null, 24, null, 27, null, null, null, null, null, null, 12, null, null, null, null, null, null, null], "false": [null, 27, null, null, null, null, 36, null, null, null, 24, 12, null, 24, null, null, 27, 24, 27, null, null, null, null, 12, null, null, null, null, 5, null, 21]}, "fens_before_move": {"true": ["rnbqkbnr/pppppppp/8/8/8/8/PPPPPPPP/RNBQKBNR w KQkq - 0 1", "rnbqkbnr/pp1ppppp/8/2p5/4P3/8/PPPP1PPP/RNBQKBNR w KQkq c6 0 2", "rnbqkbnr/pp1ppppp/8/8/3pP3/8/PPP2PPP/RNBQKBNR w KQkq - 0 3", "r1bqkbnr/pp1ppppp/2n5/8/3QP3/8/PPP2PPP/RNB1KBNR w KQkq - 1 4", "r1bqkb1r/pp1ppppp/2n2n2/8/Q3P3/8/PPP2PPP/RNB1KBNR w KQkq - 3 5", "r1bqkb1r/pp1p1ppp/2n1pn2/8/Q3P3/2N5/PPP2PPP/R1B1KBNR w KQkq - 0 6", "r1bqkb1r/pp3ppp/2nppn2/8/Q3P3/2N2N2/PPP2PPP/R1B1KB1R w KQkq - 0 7", "r1bqkb1r/pp3ppp/2n1pn2/4p3/Q7/2N2N2/PPP2PPP/R1B1KB1R w KQkq - 0 8", "r2qkb1r/pp1b1ppp/2n1pn2/4p3/Q7/1PN2N2/P1P2PPP/R1B1KB1R w KQkq - 1 9", "r2qk2r/pp1b1ppp/2n1pn2/2b1p3/Q7/1PN2NP1/P1P2P1P/R1B1KB1R w KQkq - 1 10", "r2qk2r/pp1b1ppp/4pn2/2b1p3/Q2n4/1PN2NP1/P1P1BP1P/R1B1K2R w KQkq - 3 11", "r2qk2r/pp3ppp/4pn2/2b1p3/b2n4/1PN2NP1/P1P1BP1P/R1B2RK1 w kq - 0 12", "r2qk2r/pp3ppp/4pn2/2b1p3/N7/1P3NP1/P1P1nP1P/R1B2RK1 w kq - 0 13", "r2qk2r/pp3ppp/4pn2/2b1p3/N7/1Pn2NP1/P1P2PKP/R1B2R2 w kq - 2 14", "r2qk2r/pp3ppp/4pn2/2b1p3/n7/1P3NP1/PBP2PKP/R4R2 w kq - 0 15", "r2qk2r/pp3ppp/4pn2/2b5/P3p3/5NP1/PBP2PKP/R4R2 w kq - 0 16", "r2qk2r/pp3ppp/4pn2/8/P2bp3/6P1/PBP2PKP/R4RN1 w kq - 2 17", "r3k2r/pp3ppp/4pn2/8/P2qp3/6P1/P1P2PKP/R4RN1 w kq - 0 18", "r3k2r/pp3ppp/4pn2/8/q3p3/6P1/P1P1NPKP/R4R2 w kq - 0 19", "r3k2r/pp3ppp/4pn2/8/3qp3/6P1/P1P2PKP/R4R2 w kq - 0 20", "r3k2r/pp3ppp/4pn2/8/4p3/2q3PP/P1P2PK1/R4R2 w kq - 1 21", "r3k2r/pp3ppp/4pn2/8/4p3/5qPP/P1P2P2/R4RK1 w kq - 3 22", "r3k2r/pp3ppp/4pn2/8/8/4pqPP/P1P2P2/4RRK1 w kq - 0 23", "r3k2r/pp3ppp/4pn2/8/6P1/5q1P/P1P1pP2/4RRK1 w kq - 0 24", "r3k2r/pp3ppp/4pn2/8/6P1/7P/P1P1qP2/5RK1 w kq - 0 25", "2kr3r/pp3ppp/4pn2/8/6P1/P6P/2P1qP2/5RK1 w - - 1 26", "2kr3r/pp3ppp/4p3/8/4n1P1/P1P4P/4qP2/5RK1 w - - 1 27", "2k4r/pp3ppp/4p3/8/4n1P1/P1P4P/4qPK1/3r1R2 w - - 3 28", "2k4r/pp3ppp/4p3/6P1/4n3/P1P4P/4qPK1/4rR2 w - - 1 29", "2k4r/pp3ppp/4p1P1/8/4n3/P1P4P/5PK1/4rq2 w - - 0 30", "2k4r/pp3ppp/4p1P1/8/4n3/P1P2K1P/5P2/4r2q w - - 2 31"], "false": ["rnbqkbnr/pppppppp/8/8/4P3/8/PPPP1PPP/RNBQKBNR b KQkq e3 0 1", "rnbqkbnr/pp1ppppp/8/2p5/3PP3/8/PPP2PPP/RNBQKBNR b KQkq d3 0 2", "rnbqkbnr/pp1ppppp/8/8/3QP3/8/PPP2PPP/RNB1KBNR b KQkq - 0 3", "r1bqkbnr/pp1ppppp/2n5/8/Q3P3/8/PPP2PPP/RNB1KBNR b KQkq - 2 4", "r1bqkb1r/pp1ppppp/2n2n2/8/Q3P3/2N5/PPP2PPP/R1B1KBNR b KQkq - 4 5", "r1bqkb1r/pp1p1ppp/2n1pn2/8/Q3P3/2N2N2/PPP2PPP/R1B1KB1R b KQkq - 1 6", "r1bqkb1r/pp3ppp/2nppn2/4P3/Q7/2N2N2/PPP2PPP/R1B1KB1R b KQkq - 0 7", "r1bqkb1r/pp3ppp/2n1pn2/4p3/Q7/1PN2N2/P1P2PPP/R1B1KB1R b KQkq - 0 8", "r2qkb1r/pp1b1ppp/2n1pn2/4p3/Q7/1PN2NP1/P1P2P1P/R1B1KB1R b KQkq - 0 9", "r2qk2r/pp1b1ppp/2n1pn2/2b1p3/Q7/1PN2NP1/P1P1BP1P/R1B1K2R b KQkq - 2 10", "r2qk2r/pp1b1ppp/4pn2/2b1p3/Q2n4/1PN2NP1/P1P1BP1P/R1B2RK1 b kq - 4 11", "r2qk2r/pp3ppp/4pn2/2b1p3/N2n4/1P3NP1/P1P1BP1P/R1B2RK1 b kq - 0 12", "r2qk2r/pp3ppp/4pn2/2b1p3/N7/1P3NP1/P1P1nPKP/R1B2R2 b kq - 1 13", "r2qk2r/pp3ppp/4pn2/2b1p3/N7/1Pn2NP1/PBP2PKP/R4R2 b kq - 3 14", "r2qk2r/pp3ppp/4pn2/2b1p3/P7/5NP1/PBP2PKP/R4R2 b kq - 0 15", "r2qk2r/pp3ppp/4pn2/2b5/P3p3/6P1/PBP2PKP/R4RN1 b kq - 1 16", "r2qk2r/pp3ppp/4pn2/8/P2Bp3/6P1/P1P2PKP/R4RN1 b kq - 0 17", "r3k2r/pp3ppp/4pn2/8/P2qp3/6P1/P1P1NPKP/R4R2 b kq - 1 18", "r3k2r/pp3ppp/4pn2/8/q2Np3/6P1/P1P2PKP/R4R2 b kq - 1 19", "r3k2r/pp3ppp/4pn2/8/3qp3/6PP/P1P2PK1/R4R2 b kq - 0 20", "r3k2r/pp3ppp/4pn2/8/4p3/2q3PP/P1P2P2/R4RK1 b kq - 2 21", "r3k2r/pp3ppp/4pn2/8/4p3/5qPP/P1P2P2/4RRK1 b kq - 4 22", "r3k2r/pp3ppp/4pn2/8/6P1/4pq1P/P1P2P2/4RRK1 b kq - 0 23", "r3k2r/pp3ppp/4pn2/8/6P1/5q1P/P1P1RP2/5RK1 b kq - 0 24", "r3k2r/pp3ppp/4pn2/8/6P1/P6P/2P1qP2/5RK1 b kq - 0 25", "2kr3r/pp3ppp/4pn2/8/6P1/P1P4P/4qP2/5RK1 b - - 0 26", "2kr3r/pp3ppp/4p3/8/4n1P1/P1P4P/4qPK1/5R2 b - - 2 27", "2k4r/pp3ppp/4p3/6P1/4n3/P1P4P/4qPK1/3r1R2 b - - 0 28", "2k4r/pp3ppp/4p1P1/8/4n3/P1P4P/4qPK1/4rR2 b - - 0 29", "2k4r/pp3ppp/4p1P1/8/4n3/P1P2K1P/5P2/4rq2 b - - 1 30", "2k4r/pp3ppp/4p1P1/8/4n3/P1P2K1P/5P2/4r2q b - - 3 31"]}, "fens_after_move": {"true": ["rnbqkbnr/pppppppp/8/8/4P3/8/PPPP1PPP/RNBQKBNR b KQkq e3 0 1", "rnbqkbnr/pp1ppppp/8/2p5/3PP3/8/PPP2PPP/RNBQKBNR b KQkq d3 0 2", "rnbqkbnr/pp1ppppp/8/8/3QP3/8/PPP2PPP/RNB1KBNR b KQkq - 0 3", "r1bqkbnr/pp1ppppp/2n5/8/Q3P3/8/PPP2PPP/RNB1KBNR b KQkq - 2 4", "r1bqkb1r/pp1ppppp/2n2n2/8/Q3P3/2N5/PPP2PPP/R1B1KBNR b KQkq - 4 5", "r1bqkb1r/pp1p1ppp/2n1pn2/8/Q3P3/2N2N2/PPP2PPP/R1B1KB1R b KQkq - 1 6", "r1bqkb1r/pp3ppp/2nppn2/4P3/Q7/2N2N2/PPP2PPP/R1B1KB1R b KQkq - 0 7", "r1bqkb1r/pp3ppp/2n1pn2/4p3/Q7/1PN2N2/P1P2PPP/R1B1KB1R b KQkq - 0 8", "r2qkb1r/pp1b1ppp/2n1pn2/4p3/Q7/1PN2NP1/P1P2P1P/R1B1KB1R b KQkq - 0 9", "r2qk2r/pp1b1ppp/2n1pn2/2b1p3/Q7/1PN2NP1/P1P1BP1P/R1B1K2R b KQkq - 2 10", "r2qk2r/pp1b1ppp/4pn2/2b1p3/Q2n4/1PN2NP1/P1P1BP1P/R1B2RK1 b kq - 4 11", "r2qk2r/pp3ppp/4pn2/2b1p3/N2n4/1P3NP1/P1P1BP1P/R1B2RK1 b kq - 0 12", "r2qk2r/pp3ppp/4pn2/2b1p3/N7/1P3NP1/P1P1nPKP/R1B2R2 b kq - 1 13", "r2qk2r/pp3ppp/4pn2/2b1p3/N7/1Pn2NP1/PBP2PKP/R4R2 b kq - 3 14", "r2qk2r/pp3ppp/4pn2/2b1p3/P7/5NP1/PBP2PKP/R4R2 b kq - 0 15", "r2qk2r/pp3ppp/4pn2/2b5/P3p3/6P1/PBP2PKP/R4RN1 b kq - 1 16", "r2qk2r/pp3ppp/4pn2/8/P2Bp3/6P1/P1P2PKP/R4RN1 b kq - 0 17", "r3k2r/pp3ppp/4pn2/8/P2qp3/6P1/P1P1NPKP/R4R2 b kq - 1 18", "r3k2r/pp3ppp/4pn2/8/q2Np3/6P1/P1P2PKP/R4R2 b kq - 1 19", "r3k2r/pp3ppp/4pn2/8/3qp3/6PP/P1P2PK1/R4R2 b kq - 0 20", "r3k2r/pp3ppp/4pn2/8/4p3/2q3PP/P1P2P2/R4RK1 b kq - 2 21", "r3k2r/pp3ppp/4pn2/8/4p3/5qPP/P1P2P2/4RRK1 b kq - 4 22", "r3k2r/pp3ppp/4pn2/8/6P1/4pq1P/P1P2P2/4RRK1 b kq - 0 23", "r3k2r/pp3ppp/4pn2/8/6P1/5q1P/P1P1RP2/5RK1 b kq - 0 24", "r3k2r/pp3ppp/4pn2/8/6P1/P6P/2P1qP2/5RK1 b kq - 0 25", "2kr3r/pp3ppp/4pn2/8/6P1/P1P4P/4qP2/5RK1 b - - 0 26", "2kr3r/pp3ppp/4p3/8/4n1P1/P1P4P/4qPK1/5R2 b - - 2 27", "2k4r/pp3ppp/4p3/6P1/4n3/P1P4P/4qPK1/3r1R2 b - - 0 28", "2k4r/pp3ppp/4p1P1/8/4n3/P1P4P/4qPK1/4rR2 b - - 0 29", "2k4r/pp3ppp/4p1P1/8/4n3/P1P2K1P/5P2/4rq2 b - - 1 30", "2k4r/pp3ppp/4p1P1/8/4n3/P1P2K1P/5P2/4r2q b - - 3 31"], "false": ["rnbqkbnr/pp1ppppp/8/2p5/4P3/8/PPPP1PPP/RNBQKBNR w KQkq c6 0 2", "rnbqkbnr/pp1ppppp/8/8/3pP3/8/PPP2PPP/RNBQKBNR w KQkq - 0 3", "r1bqkbnr/pp1ppppp/2n5/8/3QP3/8/PPP2PPP/RNB1KBNR w KQkq - 1 4", "r1bqkb1r/pp1ppppp/2n2n2/8/Q3P3/8/PPP2PPP/RNB1KBNR w KQkq - 3 5", "r1bqkb1r/pp1p1ppp/2n1pn2/8/Q3P3/2N5/PPP2PPP/R1B1KBNR w KQkq - 0 6", "r1bqkb1r/pp3ppp/2nppn2/8/Q3P3/2N2N2/PPP2PPP/R1B1KB1R w KQkq - 0 7", "r1bqkb1r/pp3ppp/2n1pn2/4p3/Q7/2N2N2/PPP2PPP/R1B1KB1R w KQkq - 0 8", "r2qkb1r/pp1b1ppp/2n1pn2/4p3/Q7/1PN2N2/P1P2PPP/R1B1KB1R w KQkq - 1 9", "r2qk2r/pp1b1ppp/2n1pn2/2b1p3/Q7/1PN2NP1/P1P2P1P/R1B1KB1R w KQkq - 1 10", "r2qk2r/pp1b1ppp/4pn2/2b1p3/Q2n4/1PN2NP1/P1P1BP1P/R1B1K2R w KQkq - 3 11", "r2qk2r/pp3ppp/4pn2/2b1p3/b2n4/1PN2NP1/P1P1BP1P/R1B2RK1 w kq - 0 12", "r2qk2r/pp3ppp/4pn2/2b1p3/N7/1P3NP1/P1P1nP1P/R1B2RK1 w kq - 0 13", "r2qk2r/pp3ppp/4pn2/2b1p3/N7/1Pn2NP1/P1P2PKP/R1B2R2 w kq - 2 14", "r2qk2r/pp3ppp/4pn2/2b1p3/n7/1P3NP1/PBP2PKP/R4R2 w kq - 0 15", "r2qk2r/pp3ppp/4pn2/2b5/P3p3/5NP1/PBP2PKP/R4R2 w kq - 0 16", "r2qk2r/pp3ppp/4pn2/8/P2bp3/6P1/PBP2PKP/R4RN1 w kq - 2 17", "r3k2r/pp3ppp/4pn2/8/P2qp3/6P1/P1P2PKP/R4RN1 w kq - 0 18", "r3k2r/pp3ppp/4pn2/8/q3p3/6P1/P1P1NPKP/R4R2 w kq - 0 19", "r3k2r/pp3ppp/4pn2/8/3qp3/6P1/P1P2PKP/R4R2 w kq - 0 20", "r3k2r/pp3ppp/4pn2/8/4p3/2q3PP/P1P2PK1/R4R2 w kq - 1 21", "r3k2r/pp3ppp/4pn2/8/4p3/5qPP/P1P2P2/R4RK1 w kq - 3 22", "r3k2r/pp3ppp/4pn2/8/8/4pqPP/P1P2P2/4RRK1 w kq - 0 23", "r3k2r/pp3ppp/4pn2/8/6P1/5q1P/P1P1pP2/4RRK1 w kq - 0 24", "r3k2r/pp3ppp/4pn2/8/6P1/7P/P1P1qP2/5RK1 w kq - 0 25", "2kr3r/pp3ppp/4pn2/8/6P1/P6P/2P1qP2/5RK1 w - - 1 26", "2kr3r/pp3ppp/4p3/8/4n1P1/P1P4P/4qP2/5RK1 w - - 1 27", "2k4r/pp3ppp/4p3/8/4n1P1/P1P4P/4qPK1/3r1R2 w - - 3 28", "2k4r/pp3ppp/4p3/6P1/4n3/P1P4P/4qPK1/4rR2 w - - 1 29", "2k4r/pp3ppp/4p1P1/8/4n3/P1P4P/5PK1/4rq2 w - - 0 30", "2k4r/pp3ppp/4p1P1/8/4n3/P1P2K1P/5P2/4r2q w - - 2 31", "2k4r/pp3ppp/4p1P1/8/4n3/P1P2q1P/5P2/4r3 w - - 0 32"]}, "winner_color": false, "win_reason": {"type": "WinReason", "value": "KING_CAPTURE"}}